<vars xmlns="http://www.idiominc.com/opentopic/vars">
  <variable id="blank_page">Questa pagina è stata lasciata intenzionalmente vuota</variable>
  <variable id="#table-continued">Table continued&#x2026;</variable>
  <variable id="Figure"> Figura: <param ref-name="title"/></variable>
  <variable id="Table">Tabella: <param ref-name="title"/></variable>
  <variable id="Chapter with number"></variable>
  <variable id="Table of Contents Chapter"></variable>
  <variable id="Table of Contents Appendix">Appendice:&#xA0;</variable>
</vars>